Flask_SQLA2api-0.2.1.dist-info/DESCRIPTION.rst
Flask_SQLA2api-0.2.1.dist-info/LICENSE.txt
Flask_SQLA2api-0.2.1.dist-info/METADATA
Flask_SQLA2api-0.2.1.dist-info/RECORD
Flask_SQLA2api-0.2.1.dist-info/WHEEL
Flask_SQLA2api-0.2.1.dist-info/metadata.json
Flask_SQLA2api-0.2.1.dist-info/top_level.txt
flask_sqla2api/__init__.py
flask_sqla2api/models.py
flask_sqla2api/sqla2api.py
