Metadata-Version: 2.0
Name: Flask-SQLA2api
Version: 0.2.1
Summary: Flask-SQLAlchemy Model to API in one line of code
Home-page: https://github.com/acifani/flask-sqla2api
Author: Alessandro Cifani
Author-email: alessandro.cifani@gmail.com
License: BSD
Platform: UNKNOWN
Classifier: Development Status :: 3 - Alpha
Classifier: Environment :: Web Environment
Classifier: Intended Audience :: Developers
Classifier: License :: OSI Approved :: BSD License
Classifier: Operating System :: OS Independent
Classifier: Topic :: Internet :: WWW/HTTP :: Dynamic Content
Classifier: Topic :: Software Development :: Libraries :: Python Modules
Classifier: Programming Language :: Python
Requires-Dist: Flask (>=0.12.2)
Requires-Dist: Flask-SQLAlchemy (>=2.2)
Provides-Extra: test
Requires-Dist: pytest; extra == 'test'
